MANIFEST.in
README.rst
setup.py
vcversioner.py
version.txt
vcversioner.egg-info/PKG-INFO
vcversioner.egg-info/SOURCES.txt
vcversioner.egg-info/dependency_links.txt
vcversioner.egg-info/entry_points.txt
vcversioner.egg-info/top_level.txt