Metadata-Version: 1.1
Name: vcversioner
Version: 0.13.1.0
Summary: Use version control tags to discover version numbers
Home-page: https://github.com/habnabit/vcversioner
Author: Aaron Gallagher
Author-email: _@habnab.it
License: ISC
Platform: UNKNOWN
Classifier: Development Status :: 3 - Alpha
Classifier: Intended Audience :: Developers
Classifier: License :: OSI Approved :: ISC License (ISCL)
Classifier: Operating System :: OS Independent
Classifier: Programming Language :: Python :: 2
Classifier: Programming Language :: Python :: 2.6
Classifier: Programming Language :: Python :: 2.7
Classifier: Programming Language :: Python :: 3
Classifier: Programming Language :: Python :: 3.2
Classifier: Programming Language :: Python :: 3.3
Classifier: Topic :: Software Development :: Version Control
